{
  "data": {
    "id": "5f6586aa-7e6d-4b60-9adc-8b127081153f",
    "type": "dataset",
    "attributes": {
      "name": "GFW Integrated Deforestation Alert",
      "slug": "GFW-Integrated-Deforestation-Alert",
      "type": null,
      "subtitle": "Combines the GLAD-S, GLAD and RADD alert layers",
      "application": ["forest-atlas"],
      "dataPath": null,
      "attributesPath": null,
      "connectorType": "wms",
      "provider": "wms",
      "userId": "5b3a57251b3a8854b6338faa",
      "connectorUrl": "https://dev-tiles.globalforestwatch.org/gfw_integrated_alerts/latest/default/%7Bz%7D/%7Bx%7D/%7By%7D.png",
      "sources": [],
      "tableName": null,
      "status": "saved",
      "published": true,
      "overwrite": false,
      "mainDateField": null,
      "env": "production",
      "geoInfo": false,
      "protected": false,
      "legend": {
        "date": [],
        "region": [],
        "country": [],
        "nested": [],
        "integer": [],
        "short": [],
        "byte": [],
        "double": [],
        "float": [],
        "half_float": [],
        "scaled_float": [],
        "boolean": [],
        "binary": [],
        "text": [],
        "keyword": []
      },
      "clonedHost": {},
      "errorMessage": null,
      "taskId": null,
      "createdAt": "2022-02-11T20:07:39.900Z",
      "updatedAt": "2022-02-11T20:07:39.900Z",
      "dataLastUpdated": null,
      "widgetRelevantProps": [],
      "layerRelevantProps": []
    }
  }
}
